tox_pdm-0.7.2.dist-info/METADATA
tox_pdm-0.7.2.dist-info/WHEEL
tox_pdm-0.7.2.dist-info/entry_points.txt
tox_pdm-0.7.2.dist-info/licenses/LICENSE
tox_pdm/__init__.py
tox_pdm/plugin.py
tox_pdm/utils.py
tox_pdm-0.7.2.dist-info/RECORD
