Metadata-Version: 2.1
Name: tox-pdm
Version: 0.7.2
Summary: A plugin for tox that utilizes PDM as the package manager and installer
Keywords: tox testing pdm
Author-Email: Frost Ming <me@frostming.com>
License: MIT
Classifier: Development Status :: 4 - Beta
Classifier: Intended Audience :: Developers
Classifier: Programming Language :: Python :: 3
Classifier: Programming Language :: Python :: 3.7
Classifier: Programming Language :: Python :: 3.8
Classifier: Programming Language :: Python :: 3.9
Classifier: Programming Language :: Python :: 3.10
Classifier: Programming Language :: Python :: 3.11
Project-URL: Homepage, https://github.com/pdm-project/tox-pdm
Project-URL: Repository, https://github.com/pdm-project/tox-pdm
Requires-Python: >=3.7
Requires-Dist: tox>=4.0
Requires-Dist: tomli; python_version < "3.11"
Requires-Dist: pytest>=6.2; extra == "test"
Requires-Dist: coverage[toml]<6.4,>=5.5; extra == "test"
Requires-Dist: flake8>=3.8; extra == "lint"
Requires-Dist: black>=20.8b1; extra == "lint"
Provides-Extra: test
Provides-Extra: lint
